{"hash":"f5f6bf98bd95e769321482904cbbd488f77922fd","data":{"entry":{"id":"340787200-1001352129329","title":"Golang разработчик","text":"#вакансия #Москва #senior #Go #fulltime #офис #удаленка  \nВакансия: Lead or Senior Golang Developer \nКомпания: Skytech Solutions\nГород: Moscow/Malta\nФормат работы: офис или удаленка (на выбор кандидата)\nЗанятость: полная\nВилка заработной платы: от 180 000 - 230 000 р на руки\n\nТребуемый опыт работы: 3–6 лет.\nПолная занятость, полный день\n\nОбязанности:\nСоздание высоконагруженных сервисов / микро-сервисов;\nРазработка интеграции с внешними сервисами;\nРазработка платформы для Betting / Gambling;\nРазработка надежной, безопасной и безотказной экосистемы;\nРешение сложных и интересных задач;\n\nТребования:\nИметь опыт коммерческой разработки ПО на Go не менее 3-х лет, отличное знание языка и экосистемы;\nПонимание многопоточности, параллельных вычислений и широко используемых структур данных и алгоритмов;\nПонимание основных паттернов проектирования;\nУмение работать с контролем версий Git;\nУверенно знаете стек TCP / IP;\nЗнаете RFC стандартны HTTP / WebSockets;\nРаботаете с REST / GraphQL;\nЗнание лучших практик разработки микро-сервисных архитектур, Docker и опыт production релизов совместно с девопс инженерами;\nИмеете опыт написания высоконагруженных систем;\nРаботаете unix-подобными системами;\nОтличное знание SQL и одной из реляционных СУБД.\nСильные навыки решения проблем, желание работать в команде;\n\nБудет плюсом:\nПрофильное высшее образование (математическое или техническое);\nИмеете опыт разработки подобных решений (Ставки на спорт/Gambling/Poker/Trade)\nЗнание Алгоритмов\nОпыт работы с Графовыми базами данных;\n\nSoft skills:\nРешать поставленные задачи максимально эффективно в поставленный срок;\nЯвляться командным разработчиком, слышать других и учитывать чужое мнение;\nПонимать, что не надо делать overhead там, где это не надо;\nБыть самостоятельным и уметь брать на себя ответственность за свои решения;\nСчитать тестирование неотъемлемой частью разработки;\nСпокойно относиться к техническому долгу, так как это нормальный этап в развитии проекта;\n\nНемного о проекте:\nВ связи с расширением нашего портфеля проектов, мы находится в поисках квалифицированных разработчиков ПО.\nМы разрабатываем  высоконагруженный проект, связанный со ставками на sport/e-sport , фактически - это биржа ставок со своими сопутствующими сервисами, в нашем случае упор идет на Algo-trading, bot platform, AI и алгоритмы. Проект очень сложный и интересный, нет Legacy кода, все разрабатывается с 0. Будем рады видеть тебя в своих рядах.\nНаш стек :\nLinux, Go, PostgreSQL, Git, ArangoDB, Tarantool, Kafka, Redis.\n\nМы предлагаем:\nВозможность карьерного и профессионального роста в международной компании;\nРабота по контракту с зарубежной компанией (Мальта);\nВысокий уровень заработной платы;\nБонусы и премии по итогам выполненных задач;\nРазработка ведется по гибким методологиям;\nВозможна удаленная работа;\nГибкий график работы, но без фанатизма (главное - это качественное выполнение задач в сжатые сроки);\nПК - MacBook;\nМолодой профессиональный коллектив.\n\nКонтакты: telegram @FreddyNigma","markup":[{"type":"hashtag","offset":0,"length":9,"data":"вакансия"},{"type":"hashtag","offset":10,"length":7,"data":"Москва"},{"type":"hashtag","offset":18,"length":7,"data":"senior"},{"type":"hashtag","offset":26,"length":3,"data":"Go"},{"type":"hashtag","offset":30,"length":9,"data":"fulltime"},{"type":"hashtag","offset":40,"length":5,"data":"офис"},{"type":"hashtag","offset":46,"length":9,"data":"удаленка"},{"type":"handle","offset":2968,"length":12,"data":"FreddyNigma"}],"date":"2020-06-15T19:50:50+00:00","link":"tg://resolve?domain=gogetajobfeed&post=325","tags":[{"name":"go"},{"name":"git"},{"name":"rest"},{"name":"graphql"},{"name":"docker"},{"name":"unix"},{"name":"sql"},{"name":"linux"},{"name":"postgresql"},{"name":"kafka"},{"name":"redis"}],"cities":[{"code":"moscow","ruName":"Москва","enName":"Moscow","country":{"code":"russia","ruName":"Россия","enName":"Russia"}}],"allowsRemote":true}},"context":{"recordId":"340787200-1001352129329"}}