{"hash":"f34fd2c444a074f4e0e67d525015a008ef8e766f","data":{"entry":{"id":"1433403392-1001091028994","title":"Java developer","text":"#java #middle+ #senoir #fulltime #Москва #Ярославль\nJava Developer\nКомпания: Solit Clouds\nЛокация: Москва/Ярославль\nЗп: от 180к до 250к \nКонтакты: @IrinaTishkina\n\nНаша сфера деятельности – это создание уникальных решений в области информатизации медицины, банковской сферы, финансовых организаций, складских систем и других, существенно влияющих на жизнь и здоровье, областей.\n✅Проекты:\n•  Разработка собственной Big Data / BI платформы\n•  Разработка решений в одном из самых масштабных проектов Москвы\n✅Во что предстоит погрузиться:\n•  Участие в проектировании и разработке высоконагруженных облачных решений;\n•  Предложение архитектурных и технических решений;\n•  Коммуникация с аналитиками: необходимо понимать бизнес задачу и предлагать оптимальное техническое решение;\n•  Проектирование интерфейсов и сервисов внутреннего обмена данными;\n•  Контроль качества технических решений, разрабатываемых командой.\n✅Какой опыт может быть интересен:\n•  Умение читать иностранную документацию;\n•  Способность и желание развиваться и изучать новые технологии;\n•  Знание и умение применять паттерны проектирования;\n•  Отличные знания Java и опыт создания приложений с нуля;\n•  Опыт работы с реляционными БД;\n•  Отличные знание SQL, навыки оптимизации планов запросов;\n✅Знание технологий:\n•  Java (Java SE, JEE);\n•  Spring Framework;\n•  Hibernate;\n•  Maven/Gradle;\n•  Oracle, PostgreSQL;\n•  Git/SVN/Mercurial;\n•  TomCat/Undertow/WildFly/GlassFish;\n•  SОAP, REST, WebSockets, JMS.\n✅Мы предлагаем:\n•  Участие в интересных масштабных проектах федерального уровня;\n•  Продуктовые команды, обмен опытом и наставничество;\n•  Конкурентная заработная плата и официальное оформление по ТК;\n•  Работа по гибким методологиям;\n•  Ежегодная оценка и пересмотр условий труда;\n•  Гибкое начало рабочего дня и социальный пакет.","markup":[{"type":"hashtag","offset":0,"length":5,"data":"java"},{"type":"hashtag","offset":6,"length":7,"data":"middle"},{"type":"hashtag","offset":15,"length":7,"data":"senoir"},{"type":"hashtag","offset":23,"length":9,"data":"fulltime"},{"type":"hashtag","offset":33,"length":7,"data":"Москва"},{"type":"hashtag","offset":41,"length":10,"data":"Ярославль"},{"type":"handle","offset":147,"length":14,"data":"IrinaTishkina"}],"date":"2020-04-10T07:57:38+00:00","link":"tg://resolve?domain=jvmjobs&post=1367","tags":[{"name":"java"},{"name":"jvm"},{"name":"sql"},{"name":"spring"},{"name":"hibernate"},{"name":"maven"},{"name":"gradle"},{"name":"oracle"},{"name":"postgresql"},{"name":"git"},{"name":"svn"},{"name":"mercurial"},{"name":"tomcat"},{"name":"rest"}],"cities":[{"code":"moscow","ruName":"Москва","enName":"Moscow","country":{"code":"russia","ruName":"Россия","enName":"Russia"}},{"code":"yaroslavl","ruName":"Ярославль","enName":"Yaroslavl","country":{"code":"russia","ruName":"Россия","enName":"Russia"}}],"allowsRemote":false}},"context":{"recordId":"1433403392-1001091028994","tags":["java","jvm","sql","spring","hibernate","maven","gradle","oracle","postgresql","git","svn","mercurial","tomcat","rest"]}}